netdisco/__init__.py
netdisco/__main__.py
netdisco/const.py
netdisco/discovery.py
netdisco/mdns.py
netdisco/service.py
netdisco/ssdp.py
netdisco/util.py
netdisco/discoverables/__init__.py
netdisco/discoverables/bluesound.py
netdisco/discoverables/bose_soundtouch.py
netdisco/discoverables/enigma2.py
netdisco/discoverables/frontier_silicon.py
netdisco/discoverables/lg_smart_device.py
netdisco/discoverables/openhome.py
netdisco/discoverables/sabnzbd.py
netdisco/discoverables/yamaha.py
netdisco-3.0.0.dist-info/LICENSE.md
netdisco-3.0.0.dist-info/METADATA
netdisco-3.0.0.dist-info/WHEEL
netdisco-3.0.0.dist-info/top_level.txt
netdisco-3.0.0.dist-info/RECORD
