Metadata-Version: 2.1
Name: netdisco
Version: 3.0.0
Summary: Discover devices on your local network
Home-page: https://github.com/home-assistant/netdisco
Author: Paulus Schoutsen
Author-email: Paulus@PaulusSchoutsen.nl
License: Apache License 2.0
Platform: UNKNOWN
Classifier: Development Status :: 5 - Production/Stable
Classifier: Environment :: Console
Classifier: Intended Audience :: Developers
Classifier: License :: OSI Approved :: Apache Software License
Classifier: Operating System :: POSIX
Classifier: Programming Language :: Python :: 3
Classifier: Topic :: Utilities
Classifier: Topic :: Home Automation
Classifier: Topic :: System :: Networking
Requires-Python: >=3
License-File: LICENSE.md
